dojo_pkg/__init__.py
dojo_pkg/dojo.py
dojo_pkg_claudialorenzon-0.0.1.dist-info/LICENSE
dojo_pkg_claudialorenzon-0.0.1.dist-info/METADATA
dojo_pkg_claudialorenzon-0.0.1.dist-info/WHEEL
dojo_pkg_claudialorenzon-0.0.1.dist-info/top_level.txt
dojo_pkg_claudialorenzon-0.0.1.dist-info/RECORD
