Metadata-Version: 2.1
Name: dojo-pkg-claudialorenzon
Version: 0.0.1
Summary: Un piccolo package per il corso di Python 3
Home-page: https://github.com/claudialorenzon/python3_dojo
Author: Claudia Lorenzon
Author-email: claudialorenzon@yahoo.it
License: UNKNOWN
Platform: UNKNOWN
Classifier: Programming Language :: Python :: 3
Classifier: License :: OSI Approved :: MIT License
Classifier: Operating System :: OS Independent
Requires-Python: >=3.6
